oyaml.py
oyaml-0.9.dist-info/LICENSE
oyaml-0.9.dist-info/METADATA
oyaml-0.9.dist-info/WHEEL
oyaml-0.9.dist-info/top_level.txt
oyaml-0.9.dist-info/RECORD
