Metadata-Version: 1.0
Name: oyaml
Version: 0.9
Summary: Ordered YAML: drop-in replacement for PyYAML which preserves dict ordering
Home-page: https://github.com/wimglenn/oyaml
Author: Wim Glenn
Author-email: hey@wimglenn.com
License: MIT
Platform: UNKNOWN
